shakemyhand_walkthrough/__init__.py
shakemyhand_walkthrough/shakemyhand_walkthrough.py
shakemyhand_walkthrough-0.2.3.dist-info/LICENSE
shakemyhand_walkthrough-0.2.3.dist-info/METADATA
shakemyhand_walkthrough-0.2.3.dist-info/WHEEL
shakemyhand_walkthrough-0.2.3.dist-info/entry_points.txt
shakemyhand_walkthrough-0.2.3.dist-info/top_level.txt
shakemyhand_walkthrough-0.2.3.dist-info/RECORD
