Metadata-Version: 2.2
Name: shakemyhand-walkthrough
Version: 0.2.3
Summary: Interactive Python walkthrough for the 'Shake My Hand' 2025 Iris CTF challenge
Home-page: https://github.com/admiralsyn-ackbar/shakemyhand-walkthrough
Author: Admiral SYN-ACKbar
Author-email: admiral@admiralsyn-ackbar.com
Classifier: Programming Language :: Python :: 3
Classifier: License :: OSI Approved :: GNU General Public License v3 (GPLv3)
Classifier: Operating System :: OS Independent
Requires-Python: >=3.7
License-File: LICENSE
Requires-Dist: scapy>=2.5.0
Dynamic: author
Dynamic: author-email
Dynamic: classifier
Dynamic: description
Dynamic: description-content-type
Dynamic: home-page
Dynamic: requires-dist
Dynamic: requires-python
Dynamic: summary
